gca_analyzer/__init__.py
gca_analyzer/__main__.py
gca_analyzer/__version__.py
gca_analyzer/analyzer.py
gca_analyzer/config.py
gca_analyzer/llm_processor.py
gca_analyzer/logger.py
gca_analyzer/main.py
gca_analyzer/utils.py
gca_analyzer/visualizer.py
gca_analyzer/data/sample_conversation.csv
gca_analyzer-0.4.7.dist-info/licenses/LICENSE
tests/__init__.py
tests/test_analyzer.py
tests/test_analyzer_edge_cases.py
tests/test_llm_processor.py
tests/test_main.py
tests/test_utils.py
tests/test_visualizer.py
gca_analyzer-0.4.7.dist-info/METADATA
gca_analyzer-0.4.7.dist-info/WHEEL
gca_analyzer-0.4.7.dist-info/entry_points.txt
gca_analyzer-0.4.7.dist-info/top_level.txt
gca_analyzer-0.4.7.dist-info/RECORD
