Metadata-Version: 2.4
Name: gca_analyzer
Version: 0.4.7
Summary: A package for Group Communication Analysis with improved text processing and visualization
Home-page: https://github.com/etShaw-zh/gca_analyzer
Author: Jianjun Xiao <et_shaw@126.com>
Author-email: et_shaw@126.com
Classifier: Development Status :: 4 - Beta
Classifier: Intended Audience :: Science/Research
Classifier: License :: OSI Approved :: Apache Software License
Classifier: Programming Language :: Python :: 3
Classifier: Programming Language :: Python :: 3.9
Classifier: Programming Language :: Python :: 3.10
Classifier: Programming Language :: Python :: 3.11
Classifier: Programming Language :: Python :: 3.12
Classifier: Programming Language :: Python :: 3.13
Classifier: Topic :: Text Processing :: Linguistic
Classifier: Topic :: Scientific/Engineering :: Information Analysis
Requires-Python: >=3.9
License-File: LICENSE
Requires-Dist: pandas>=1.3.0
Requires-Dist: numpy>=1.20.0
Requires-Dist: matplotlib>=3.4.0
Requires-Dist: plotly>=5.3.0
Requires-Dist: loguru>=0.7.0
Requires-Dist: transformers>=4.30.0
Requires-Dist: sentence-transformers>=2.2.0
Requires-Dist: typing-extensions>=4.0.0
Dynamic: author
Dynamic: author-email
Dynamic: classifier
Dynamic: description
Dynamic: description-content-type
Dynamic: home-page
Dynamic: license-file
Dynamic: requires-dist
Dynamic: requires-python
Dynamic: summary
